kh2d_solver/__init__.py
kh2d_solver/cli.py
kh2d_solver/core/__init__.py
kh2d_solver/core/initial_conditions.py
kh2d_solver/core/solver.py
kh2d_solver/io/__init__.py
kh2d_solver/io/config_manager.py
kh2d_solver/io/data_handler.py
kh2d_solver/utils/__init__.py
kh2d_solver/utils/logger.py
kh2d_solver/utils/timer.py
kh2d_solver/visualization/__init__.py
kh2d_solver/visualization/animator.py
kh2d_solver-0.1.6.dist-info/LICENSE
kh2d_solver-0.1.6.dist-info/METADATA
kh2d_solver-0.1.6.dist-info/WHEEL
kh2d_solver-0.1.6.dist-info/entry_points.txt
kh2d_solver-0.1.6.dist-info/RECORD
