Metadata-Version: 2.3
Name: kh2d-solver
Version: 0.1.6
Summary: A high-performance solver for 2D Kelvin-Helmholtz instability with Numba acceleration
License: WTFPL
Keywords: fluid-dynamics,kelvin-helmholtz,instability,CFD,numerical-simulation,numba
Author: Sandy H. S. Herho
Author-email: sandy.herho@email.ucr.edu
Requires-Python: >=3.8,<4.0
Classifier: Development Status :: 4 - Beta
Classifier: Intended Audience :: Science/Research
Classifier: License :: Other/Proprietary License
Classifier: Natural Language :: English
Classifier: Operating System :: OS Independent
Classifier: Programming Language :: Python :: 3
Classifier: Programming Language :: Python :: 3.8
Classifier: Programming Language :: Python :: 3.9
Classifier: Programming Language :: Python :: 3.10
Classifier: Programming Language :: Python :: 3.11
Classifier: Programming Language :: Python :: 3.12
Classifier: Programming Language :: Python :: 3.13
Classifier: Topic :: Scientific/Engineering :: Atmospheric Science
Classifier: Topic :: Scientific/Engineering :: Physics
Requires-Dist: matplotlib (>=3.3.0)
Requires-Dist: netCDF4 (>=1.5.0)
Requires-Dist: numba (>=0.53.0)
Requires-Dist: numpy (>=1.20.0)
Requires-Dist: scipy (>=1.7.0)
Requires-Dist: tqdm (>=4.60.0)
Project-URL: Documentation, https://github.com/sandyherho/kelvin-helmholtz-2d-solver/blob/main/README.md
Project-URL: Homepage, https://github.com/sandyherho/kelvin-helmholtz-2d-solver
Project-URL: Repository, https://github.com/sandyherho/kelvin-helmholtz-2d-solver
